backlib/__init__.py
backlib/cache/aprilmenu__4866825.mp3
backlib/cache/bleepsgalore__4355204.mp3
backlib/cache/boss1__2566868.ogg
backlib/cache/boss2__2705612.ogg
backlib/cache/credits__3596955.mp3
backlib/cache/day4__1866532.mp3
backlib/cache/editor__1539857.ogg
backlib/cache/fine__1819566.ogg
backlib/cache/game1__1281219.ogg
backlib/cache/game2__1329376.ogg
backlib/cache/game3__1855682.ogg
backlib/cache/game4__2531904.ogg
backlib/cache/game5__1975980.ogg
backlib/cache/game6__1649639.ogg
backlib/cache/game7__2011976.ogg
backlib/cache/game8__2134796.ogg
backlib/cache/game9__2593090.ogg
backlib/cache/land__231417.ogg
backlib/cache/launch__1169439.ogg
backlib/cache/menu__3965128.ogg
backlib/cache/menu__985523.ogg
backlib/cache/mistake__5309360.mp3
backlib/cache/outer__2371380.ogg
backlib/cache/seq__5408424.mp3
hyperpool7-0.0.0.1.dist-info/METADATA
hyperpool7-0.0.0.1.dist-info/WHEEL
hyperpool7-0.0.0.1.dist-info/licenses/LICENSE
hyperpool7-0.0.0.1.dist-info/RECORD
